{"metadata":{"timestamp":"2024-05-04T01:36:06"},"version":1,"specVersion":"1.4","serialNumber":"urn:uuid:555b8a7a-15c1-440a-9b69-00101f045c00","bomFormat":"CycloneDX","components":[{"licenses":[{"license":{"name":"GPL-3.0"}}],"version":"3.34.0","type":"application","name":"alist"},{"licenses":[{"license":{"name":"GPLv3"}}],"name":"ChinaDNS","type":"application","version":"1.3.3"},{"licenses":[{"license":{"name":"AGPL-3.0-only"}}],"version":"2024.04.30","type":"application","name":"chinadns-ng"},{"version":"1.2.1","type":"application","name":"dns-forwarder","licenses":[{"license":{"name":"GPLv3"}}]},{"licenses":[{"license":{"name":"BSD-3-Clause"}}],"type":"application","version":"2.1","name":"dns2socks"},{"name":"dns2tcp","version":"1.1.0-240322.79782","type":"application","licenses":[{"license":{"name":"AGPL-3.0-only"}}]},{"licenses":[{"license":{"name":"MIT"}}],"name":"hysteria","version":"2.4.3","type":"application"},{"licenses":[{"license":{"name":"GPL-2.0-or-later"}}],"name":"libmbedtls12","type":"library","version":"2.28.7","cpe":"cpe:/a:arm:mbed_tls:2.28.7"},{"licenses":[{"license":{"name":"Apache-2.0"}}],"name":"libopenssl-afalg","cpe":"cpe:/a:openssl:openssl:3.0.13","version":"3.0.13","type":"library"},{"licenses":[{"license":{"name":"Apache-2.0"}}],"type":"library","cpe":"cpe:/a:openssl:openssl:3.0.13","version":"3.0.13","name":"libopenssl-conf"},{"type":"library","cpe":"cpe:/a:openssl:openssl:3.0.13","version":"3.0.13","name":"libopenssl-devcrypto","licenses":[{"license":{"name":"Apache-2.0"}}]},{"licenses":[{"license":{"name":"Apache-2.0"}}],"type":"library","version":"3.0.13","cpe":"cpe:/a:openssl:openssl:3.0.13","name":"libopenssl-legacy"},{"type":"library","version":"3.0.13","cpe":"cpe:/a:openssl:openssl:3.0.13","name":"libopenssl-padlock","licenses":[{"license":{"name":"Apache-2.0"}}]},{"type":"library","cpe":"cpe:/a:openssl:openssl:3.0.13","version":"3.0.13","name":"libopenssl3","licenses":[{"license":{"name":"Apache-2.0"}}]},{"version":"1.0.13","type":"application","name":"luci-app-alist"},{"version":"1.6.3","type":"application","name":"luci-app-chinadns","licenses":[{"license":{"name":"GPLv3"}}]},{"type":"application","version":"v0.2.13","name":"luci-app-diskman","licenses":[{"license":{"name":"AGPL-3.0"}}]},{"version":"1.6.3","type":"application","name":"luci-app-dns-forwarder","licenses":[{"license":{"name":"GPLv3"}}]},{"type":"application","version":"v0.5.26","name":"luci-app-dockerman","licenses":[{"license":{"name":"AGPL-3.0"}}]},{"name":"luci-app-homeproxy","version":"git-24.124.54443-94dbd3d","type":"application"},{"version":"1.5.20","type":"application","name":"luci-app-mosdns"},{"name":"luci-app-openclash","version":"0.46.003-beta","type":"application"},{"name":"luci-app-passwall","version":"4.77","type":"application"},{"name":"luci-app-passwall2","version":"1.29","type":"application"},{"licenses":[{"license":{"name":"GPLv3"}}],"version":"1.6.3","type":"application","name":"luci-app-redsocks2"},{"licenses":[{"license":{"name":"GPLv3"}}],"name":"luci-app-shadowsocks","type":"application","version":"2.1.1"},{"licenses":[{"license":{"name":"GPLv3"}}],"type":"application","version":"2.1.1","name":"luci-app-shadowsocks-without-ipset"},{"licenses":[{"license":{"name":"GPLv3"}}],"type":"application","version":"1.6.3","name":"luci-app-shadowvpn"},{"licenses":[{"license":{"name":"GPL-3.0-or-later"}}],"type":"application","version":"1.2024.45","name":"luci-app-smartdns"},{"licenses":[{"license":{"name":"MIT"}}],"type":"application","version":"1.0.2","name":"luci-app-vlmcsd"},{"licenses":[{"license":{"name":"MPLv2"}}],"name":"luci-app-xray","type":"application","version":"3.4.1"},{"version":"3.4.1","type":"application","name":"luci-app-xray-status","licenses":[{"license":{"name":"MPLv2"}}]},{"name":"luci-i18n-alist-zh-cn","version":"git-24.123.60014-81aad71","type":"application"},{"licenses":[{"license":{"name":"AGPL-3.0"}}],"name":"luci-i18n-diskman-pl","type":"application","version":"240504.04778"},{"licenses":[{"license":{"name":"AGPL-3.0"}}],"type":"application","version":"240504.04778","name":"luci-i18n-diskman-zh-cn"},{"name":"luci-i18n-diskman-zh-tw","version":"240504.04778","type":"application","licenses":[{"license":{"name":"AGPL-3.0"}}]},{"licenses":[{"license":{"name":"AGPL-3.0"}}],"name":"luci-i18n-dockerman-zh-cn","version":"240504.04778","type":"application"},{"name":"luci-i18n-homeproxy-zh-cn","type":"application","version":"git-24.124.54443-94dbd3d"},{"name":"luci-i18n-mosdns-zh-cn","version":"git-24.106.29027-97867ea","type":"application"},{"version":"unknown","type":"application","name":"luci-i18n-passwall-zh-cn"},{"type":"application","version":"unknown","name":"luci-i18n-passwall2-zh-cn"},{"name":"luci-i18n-smartdns-de","version":"git-24.124.40121-3aa91bb","type":"application","licenses":[{"license":{"name":"GPL-3.0-or-later"}}]},{"name":"luci-i18n-smartdns-es","type":"application","version":"git-24.124.40121-3aa91bb","licenses":[{"license":{"name":"GPL-3.0-or-later"}}]},{"licenses":[{"license":{"name":"GPL-3.0-or-later"}}],"type":"application","version":"git-24.124.40121-3aa91bb","name":"luci-i18n-smartdns-zh-cn"},{"type":"application","version":"git-24.124.40121-3aa91bb","name":"luci-i18n-smartdns-zh-tw","licenses":[{"license":{"name":"GPL-3.0-or-later"}}]},{"type":"application","version":"v0.3.4","name":"luci-lib-docker","licenses":[{"license":{"name":"AGPL-3.0"}}]},{"licenses":[{"license":{"name":"GPL-2.0-or-later"}}],"type":"application","cpe":"cpe:/a:arm:mbed_tls:2.28.7","version":"2.28.7","name":"mbedtls-util"},{"licenses":[{"license":{"name":"GPL-3.0"}}],"name":"mosdns","type":"application","version":"5.3.1"},{"type":"application","cpe":"cpe:/a:openssl:openssl:3.0.13","version":"3.0.13","name":"openssl-util","licenses":[{"license":{"name":"Apache-2.0"}}]},{"licenses":[{"license":{"name":"GPLv3"}}],"name":"shadowsocks-libev","type":"application","version":"3.3.5"},{"version":"3.3.5","type":"application","name":"shadowsocks-libev-server","licenses":[{"license":{"name":"GPLv3"}}]},{"licenses":[{"license":{"name":"GPLv3"}}],"name":"simple-obfs","type":"application","version":"0.0.5"},{"licenses":[{"license":{"name":"GPLv3"}}],"name":"simple-obfs-server","type":"application","version":"0.0.5"},{"licenses":[{"license":{"name":"GPL-3.0-or-later"}}],"version":"1.8.13","type":"application","name":"sing-box"},{"licenses":[{"license":{"name":"GPL-3.0-or-later"}}],"version":"1.2024.45","type":"application","name":"smartdns"},{"licenses":[{"license":{"name":"GPL-2.0-only"}}],"name":"tcping","type":"application","version":"0.3"},{"licenses":[{"license":{"name":"GPL-3.0"}}],"name":"v2dat","type":"application","version":"2022-12-15-47b8ee51"},{"name":"v2ray-geoip","type":"application","version":"2024-05","licenses":[{"license":{"name":"CC-BY-SA-4.0"}}]},{"licenses":[{"license":{"name":"MIT"}}],"name":"v2ray-geosite","type":"application","version":"2024-05"},{"licenses":[{"license":{"name":"MIT"}}],"type":"application","version":"svn1113","name":"vlmcsd"},{"cpe":"cpe:/a:gnu:zlib:1.2.13","version":"1.2.13","type":"library","name":"zlib","licenses":[{"license":{"name":"Zlib"}}]},{"type":"application","cpe":"cpe:/a:gnu:zlib:1.2.13","version":"1.2.13","name":"zlib-dev","licenses":[{"license":{"name":"Zlib"}}]}]}