{"arch_packages":"arm_cortex-a15_neon-vfpv4","default_packages":["base-files","busybox","ca-bundle","dnsmasq","dropbear","firewall4","fstools","kmod-ata-ahci","kmod-ata-ahci-platform","kmod-ath10k-ct","kmod-gpio-button-hotplug","kmod-leds-gpio","kmod-nft-offload","kmod-phy-qcom-ipq806x-usb","kmod-usb-dwc3-qcom","kmod-usb-ledtrig-usbport","kmod-usb-ohci","kmod-usb2","kmod-usb3","libc","libgcc","libustream-mbedtls","logd","mtd","netifd","nftables","odhcp6c","odhcpd-ipv6only","opkg","ppp","ppp-mod-pppoe","procd","procd-seccomp","procd-ujail","swconfig","uboot-envtools","uci","uclient-fetch","urandom-seed","urngd","wpad-basic-mbedtls"],"metadata_version":1,"profiles":{"netgear_r7800":{"device_packages":["ath10k-firmware-qca9984-ct","kmod-ramoops"],"image_prefix":"openwrt-23.05.3-ipq806x-generic-netgear_r7800","images":[{"filesystem":"squashfs","name":"openwrt-23.05.3-ipq806x-generic-netgear_r7800-squashfs-sysupgrade.bin","sha256":"c16b1d136c59c31f72038ebe07671505d15e978434f8f3984d5094259ba65fa6","sha256_unsigned":"0da42df1614588b9ae21e3d686e03d2e9b377b694e0f59cc6526e50635820844","type":"sysupgrade"},{"filesystem":"squashfs","name":"openwrt-23.05.3-ipq806x-generic-netgear_r7800-squashfs-factory.img","sha256":"a77dc1d4c7c9629b633b8492225197d279be5bde6a25109f35e0c5581a58816c","sha256_unsigned":"a77dc1d4c7c9629b633b8492225197d279be5bde6a25109f35e0c5581a58816c","type":"factory"}],"supported_devices":["netgear,r7800","r7800"],"titles":[{"model":"Nighthawk X4S R7800","vendor":"NETGEAR"}]}},"source_date_epoch":1711145382,"target":"ipq806x/generic","version_code":"r23809-234f1a2efa","version_number":"23.05.3"}